harambe_core/__init__.py
harambe_core/errors.py
harambe_core/normalize_url.py
harambe_core/py.typed
harambe_core/types.py
harambe_core/observer/__init__.py
harambe_core/observer/base.py
harambe_core/observer/json_observer.py
harambe_core/observer/logging_observer.py
harambe_core/observer/memory_observer.py
harambe_core/observer/serialization_observer.py
harambe_core/observer/storage_observer.py
harambe_core/observer/types.py
harambe_core/parser/__init__.py
harambe_core/parser/constants.py
harambe_core/parser/parser.py
harambe_core/parser/type_currency.py
harambe_core/parser/type_date.py
harambe_core/parser/type_email.py
harambe_core/parser/type_enum.py
harambe_core/parser/type_number.py
harambe_core/parser/type_phone_number.py
harambe_core/parser/type_price.py
harambe_core/parser/type_string.py
harambe_core/parser/type_url.py
harambe_core/parser/expression/__init__.py
harambe_core/parser/expression/evaluator.py
harambe_core/parser/expression/functions.py
harambe_core-0.77.5.dist-info/METADATA
harambe_core-0.77.5.dist-info/WHEEL
harambe_core-0.77.5.dist-info/top_level.txt
harambe_core-0.77.5.dist-info/RECORD
