Metadata-Version: 2.4
Name: harambe-core
Version: 0.77.5
Summary: Core types for harambe SDK 🐒🍌
Author-email: Adam Watkins <adam@reworkd.ai>
Requires-Python: <4.0,>=3.11
Requires-Dist: pydantic==2.9.2
Requires-Dist: dateparser==1.2.0
Requires-Dist: email-validator==2.2.0
Requires-Dist: phonenumbers==8.13.47
Requires-Dist: python-slugify==8.0.4
Requires-Dist: price-parser>=0.4.0
